TracAddCommentMacro-0.3.dist-info/DESCRIPTION.rst
TracAddCommentMacro-0.3.dist-info/METADATA
TracAddCommentMacro-0.3.dist-info/RECORD
TracAddCommentMacro-0.3.dist-info/WHEEL
TracAddCommentMacro-0.3.dist-info/entry_points.txt
TracAddCommentMacro-0.3.dist-info/metadata.json
TracAddCommentMacro-0.3.dist-info/top_level.txt
addcomment/__init__.py
addcomment/macro.py
