Metadata-Version: 2.0
Name: TracAddCommentMacro
Version: 0.3
Summary: Macro to add comments to a wiki page.
Home-page: http://trac-hacks.org/wiki/AddCommentMacro
Author: Alec Thomas
Author-email: UNKNOWN
License: BSD
Keywords: trac plugin macro comments
Platform: UNKNOWN
Classifier: Framework :: Trac
Requires-Dist: TracMacroPost (>=0.2)
